valjoux/__init__.py
valjoux/convert/__init__.py
valjoux/eta/__init__.py
valjoux/strategies/__init__.py
valjoux-0.0.1.dist-info/WHEEL
valjoux-0.0.1.dist-info/METADATA
valjoux-0.0.1.dist-info/RECORD
