Metadata-Version: 2.1
Name: valjoux
Version: 0.0.1
Summary: 
Author: hazen
Author-email: hoyeungw@outlook.com
Requires-Python: >=3.8,<4.0
Classifier: Programming Language :: Python :: 3
Classifier: Programming Language :: Python :: 3.8
Classifier: Programming Language :: Python :: 3.9
Requires-Dist: aryth (>=0.0.12)
Requires-Dist: crostab (>=0.0.11)
Requires-Dist: veho (>=0.0.10)
